Workbook

Sheet Posted Sales Invoices
A1: No. | B1: Customer No. | C1: Customer Name | D1: Posting Date | E1: Order No. | F1: Amount | G1: Location Code | H1: No. Printed | I1: Delivery Date | J1: Requested Delivery Date | K1: Shipping Agent Code | L1: Closed | M1: Canceled | N1: Corrective
A2: PS-INV229528 | B2: 13257 | C2: PFG Springfield MA | D2: 46197 | E2: S-ORD229528 | F2: 31928.4 | G2: NR-BRHL-FG | H2: 1 | I2: 46197 | J2: 46197 | K2: RT 21 | L2: =FALSE() -> FALSE | M2: =FALSE() -> FALSE | N2: =FALSE() -> FALSE
A3: PS-INV228483 | B3: 10540-03 | C3: PFG Louisville TN | D3: 46197 | E3: S-ORD228483 | F3: 24442.84 | G3: NR-BRHL-FG | H3: 2 | I3: 46197 | J3: 46197 | K3: RT 21 | L3: =FALSE() -> FALSE | M3: =FALSE() -> FALSE | N3: =FALSE() -> FALSE
A4: PS-INV227629 | B4: 10719-4 | C4: US Foods - Columbia/Lexington | D4: 46197 | E4: S-ORD227629 | F4: 6665 | G4: NR-BRHL-FG | H4: 2 | I4: 46197 | J4: 46197 | K4: RT 21 | L4: =FALSE() -> FALSE | M4: =FALSE() -> FALSE | N4: =FALSE() -> FALSE
A5: PS-INV227718 | B5: 20334 | C5: Sysco Atlanta | D5: 46196 | E5: S-ORD227718 | F5: 22383.16 | G5: NR-BRHL-FG | H5: 0 | I5: 46196 | J5: 46196 | K5: RT 21 | L5: =FALSE() -> FALSE | M5: =FALSE() -> FALSE | N5: =FALSE() -> FALSE
A6: PS-INV227566 | B6: 10511 | C6: Sysco Nashville, LLC | D6: 46196 | E6: S-ORD227566 | F6: 30238.48 | G6: NR-BRHL-FG | H6: 0 | I6: 46196 | J6: 46196 | K6: RT 21 | L6: =FALSE() -> FALSE | M6: =FALSE() -> FALSE | N6: =FALSE() -> FALSE
A7: PS-INV225932 | B7: 10719-13 | C7: US Foods - Montgomery | D7: 46196 | E7: S-ORD225932 | F7: 21862.4 | G7: NR-BRHL-FG | H7: 0 | I7: 46196 | J7: 46196 | K7: RT 21 | L7: =FALSE() -> FALSE | M7: =FALSE() -> FALSE | N7: =FALSE() -> FALSE
A8: PS-INV227180 | B8: 10899 | C8: Wood Fruitticher Grocery Co. | D8: 46195 | E8: S-ORD227180 | F8: 27636.68 | G8: NR-BRHL-FG | H8: 2 | I8: 46195 | J8: 46195 | K8: RT 21 | L8: =FALSE() -> FALSE | M8: =FALSE() -> FALSE | N8: =FALSE() -> FALSE
A9: PS-INV226973 | B9: 12438 | C9: SGC Foodservice | D9: 46195 | E9: S-ORD226973 | F9: 30466.24 | G9: NR-BRHL-FG | H9: 2 | I9: 46195 | J9: 46195 | K9: RT 21 | L9: =FALSE() -> FALSE | M9: =FALSE() -> FALSE | N9: =FALSE() -> FALSE
A10: PS-INV225785 | B10: 10549 | C10: PFG Nashville TN | D10: 46195 | E10: S-ORD225785 | F10: 2229 | G10: NR-BRHL-FG | H10: 1 | I10: 46195 | J10: 46195 | K10: RT 21 | L10: =FALSE() -> FALSE | M10: =FALSE() -> FALSE | N10: =FALSE() -> FALSE
A11: PS-INV226637 | B11: 10540-03 | C11: PFG Louisville TN | D11: 46191 | E11: S-ORD226637 | F11: 29305.64 | G11: NR-BRHL-FG | H11: 0 | I11: 46191 | J11: 46191 | K11: RT 21 | L11: =FALSE() -> FALSE | M11: =FALSE() -> FALSE | N11: =FALSE() -> FALSE
A12: PS-INV226049 | B12: 11005 | C12: Dot Foods Inc. | D12: 46191 | E12: S-ORD226049 | F12: 21388.8 | G12: NR-BRHL-FG | H12: 0 | I12: 46191 | J12: 46191 | K12: RT 21 | L12: =FALSE() -> FALSE | M12: =FALSE() -> FALSE | N12: =FALSE() -> FALSE
A13: PS-INV225952 | B13: 10700 | C13: Gordon Food Service - Douglas | D13: 46191 | E13: S-ORD225952 | F13: 30204.24 | G13: NR-BRHL-FG | H13: 0 | I13: 46191 | J13: 46191 | K13: RT 21 | L13: =FALSE() -> FALSE | M13: =FALSE() -> FALSE | N13: =FALSE() -> FALSE
... A30: PS-INV224543 | B30: 10540-03 | C30: PFG Louisville TN | D30: 46183 | E30: S-ORD224543 | F30: 22521.4 | G30: NR-BRHL-FG | H30: 2 | I30: 46183 | J30: 46183 | K30: RT 21 | L30: =FALSE() -> FALSE | M30: =FALSE() -> FALSE | N30: =FALSE() -> FALSE
A31: PS-INV223472 | B31: 10899 | C31: Wood Fruitticher Grocery Co. | D31: 46183 | E31: S-ORD223472 | F31: 26113.6 | G31: NR-BRHL-FG | H31: 2 | I31: 46183 | J31: 46183 | K31: RT 21 | L31: =TRUE() -> TRUE | M31: =FALSE() -> FALSE | N31: =FALSE() -> FALSE
A32: PS-INV223459 | B32: 10540-01 | C32: PFG Johnson City TN | D32: 46183 | E32: S-ORD223459 | F32: 12979.44 | G32: NR-BRHL-FG | H32: 2 | I32: 46183 | J32: 46183 | K32: RT 21 | L32: =FALSE() -> FALSE | M32: =FALSE() -> FALSE | N32: =FALSE() -> FALSE
A33: PS-INV222984 | B33: 12989 | C33: Sysco Little Rock Arkansas | D33: 46183 | E33: S-ORD222984 | F33: 10694.6 | G33: NR-BRHL-FG | H33: 1 | I33: 46183 | J33: 46183 | K33: RT 21 | L33: =FALSE() -> FALSE | M33: =FALSE() -> FALSE | N33: =FALSE() -> FALSE
A34: PS-INV222981 | B34: 12988 | C34: Sysco Norman OK | D34: 46183 | E34: S-ORD222981 | F34: 24920 | G34: NR-BRHL-FG | H34: 2 | I34: 46183 | J34: 46183 | K34: RT 21 | L34: =FALSE() -> FALSE | M34: =FALSE() -> FALSE | N34: =FALSE() -> FALSE
A35: PS-INV223468 | B35: 11005 | C35: Dot Foods Inc. | D35: 46182 | E35: S-ORD223468 | F35: 17111.04 | G35: NR-BRHL-FG | H35: 1 | I35: 46182 | J35: 46182 | K35: RT 21 | L35: =FALSE() -> FALSE | M35: =FALSE() -> FALSE | N35: =FALSE() -> FALSE
A36: PS-INV223450 | B36: 13128 | C36: Gordon Food Service - Shepherdsville | D36: 46182 | E36: S-ORD223450 | F36: 31873.44 | G36: NR-BRHL-FG | H36: 1 | I36: 46182 | J36: 46182 | K36: RT 21 | L36: =FALSE() -> FALSE | M36: =FALSE() -> FALSE | N36: =FALSE() -> FALSE
A37: PS-INV223008 | B37: 12438 | C37: SGC Foodservice | D37: 46182 | E37: S-ORD223008 | F37: 4545.12 | G37: NR-BRHL-FG | H37: 2 | I37: 46182 | J37: 46182 | K37: RT 21 | L37: =FALSE() -> FALSE | M37: =FALSE() -> FALSE | N37: =FALSE() -> FALSE
A38: PS-INV221682 | B38: 10547 | C38: PFG Hale TN | D38: 46182 | E38: S-ORD221682 | F38: 23098 | G38: NR-BRHL-FG | H38: 3 | I38: 46182 | J38: 46182 | K38: RT 21 | L38: =FALSE() -> FALSE | M38: =FALSE() -> FALSE | N38: =FALSE() -> FALSE
A39: PS-INV222006 | B39: 10719-2 | C39: US Foods - Fairburn | D39: 46181 | E39: S-ORD222006 | F39: 15686.28 | G39: NR-BRHL-FG | H39: 2 | I39: 46181 | J39: 46181 | K39: RT 21 | L39: =FALSE() -> FALSE | M39: =FALSE() -> FALSE | N39: =FALSE() -> FALSE
A40: PS-INV222001 | B40: 20334 | C40: Sysco Atlanta | D40: 46178 | E40: S-ORD222001 | F40: 16114.8 | G40: NR-BRHL-FG | H40: 1 | I40: 46178 | J40: 46178 | K40: RT 21 | L40: =FALSE() -> FALSE | M40: =FALSE() -> FALSE | N40: =FALSE() -> FALSE
A41: PS-INV221360 | B41: 10805 | C41: Sysco Jacksonville | D41: 46177 | E41: S-ORD221360 | F41: 18447.6 | G41: NR-BRHL-FG | H41: 2 | I41: 46177 | J41: 46177 | K41: RT 21 | L41: =FALSE() -> FALSE | M41: =FALSE() -> FALSE | N41: =FALSE() -> FALSE
A42: PS-INV223466 | B42: X10540-3 | C42: PFG Pittsburgh PA | D42: 46176 | E42: S-ORD223466 | F42: 17388 | G42: NR-BRHL-FG | H42: 1 | I42: 46176 | J42: 46176 | K42: RT 21 | L42: =FALSE() -> FALSE | M42: =FALSE() -> FALSE | N42: =FALSE() -> FALSE
A43: PS-INV221683 | B43: 13128 | C43: Gordon Food Service - Shepherdsville | D43: 46176 | E43: S-ORD221683 | F43: 32119.2 | G43: NR-BRHL-FG | H43: 1 | I43: 46176 | J43: 46176 | K43: RT 21 | L43: =FALSE() -> FALSE | M43: =FALSE() -> FALSE | N43: =FALSE() -> FALSE
... A54: PS-INV217270 | B54: 10700 | C54: Gordon Food Service - Douglas | D54: 46174 | E54: S-ORD217270 | F54: 28488.62 | G54: NR-BRHL-FG | H54: 2 | I54: 46174 | J54: 46174 | K54: RT 21 | L54: =FALSE() -> FALSE | M54: =FALSE() -> FALSE | N54: =FALSE() -> FALSE
A55: PS-INV220965 | B55: 12438 | C55: SGC Foodservice | D55: 46170 | E55: S-ORD220965 | F55: 30060.8 | G55: NR-BRHL-FG | H55: 2 | I55: 46170 | J55: 46170 | K55: RT 21 | L55: =TRUE() -> TRUE | M55: =FALSE() -> FALSE | N55: =FALSE() -> FALSE
A56: PS-INV220865 | B56: 10540-03 | C56: PFG Louisville TN | D56: 46170 | E56: S-ORD220865 | F56: 24209.52 | G56: NR-BRHL-FG | H56: 2 | I56: 46170 | J56: 46170 | K56: RT 21 | L56: =FALSE() -> FALSE | M56: =FALSE() -> FALSE | N56: =FALSE() -> FALSE
A57: PS-INV218854 | B57: 11005 | C57: Dot Foods Inc. | D57: 46170 | E57: S-ORD218854 | F57: 13902.72 | G57: NR-BRHL-FG | H57: 1 | I57: 46170 | J57: 46170 | K57: RT 21 | L57: =FALSE() -> FALSE | M57: =FALSE() -> FALSE | N57: =FALSE() -> FALSE
A58: PS-INV218758 | B58: 12988 | C58: Sysco Norman OK | D58: 46170 | E58: S-ORD218758 | F58: 26852 | G58: NR-BRHL-FG | H58: 2 | I58: 46170 | J58: 46170 | K58: RT 21 | L58: =FALSE() -> FALSE | M58: =FALSE() -> FALSE | N58: =FALSE() -> FALSE
A59: PS-INV219174 | B59: Z10700 | C59: Sysco-Charlotte | D59: 46169 | E59: S-ORD219174 | F59: 24873.36 | G59: NR-BRHL-FG | H59: 2 | I59: 46169 | J59: 46169 | K59: RT 21 | L59: =FALSE() -> FALSE | M59: =FALSE() -> FALSE | N59: =FALSE() -> FALSE
A60: PS-INV218773 | B60: 12692 | C60: United Food Service | D60: 46169 | E60: S-ORD218773 | F60: 8477 | G60: NR-BRHL-FG | H60: 0 | I60: 46169 | J60: 46169 | K60: RT 21 | L60: =FALSE() -> FALSE | M60: =FALSE() -> FALSE | N60: =FALSE() -> FALSE
A61: PS-INV219516 | B61: 10511 | C61: Sysco Nashville, LLC | D61: 46168 | E61: S-ORD219516 | F61: 20374.56 | G61: NR-BRHL-FG | H61: 4 | I61: 46168 | J61: 46168 | K61: RT 21 | L61: =FALSE() -> FALSE | M61: =FALSE() -> FALSE | N61: =FALSE() -> FALSE
A62: PS-INV218015 | B62: 10549 | C62: PFG Nashville TN | D62: 46168 | E62: S-ORD218015 | F62: 1854 | G62: NR-BRHL-FG | H62: 1 | I62: 46168 | J62: 46168 | K62: RT 21 | L62: =FALSE() -> FALSE | M62: =FALSE() -> FALSE | N62: =FALSE() -> FALSE
A63: PS-INV219937 | B63: 20334 | C63: Sysco Atlanta | D63: 46167 | E63: S-ORD219937 | F63: 21973.04 | G63: NR-BRHL-FG | H63: 1 | I63: 46171 | J63: 46171 | K63: RT 21 | L63: =FALSE() -> FALSE | M63: =FALSE() -> FALSE | N63: =FALSE() -> FALSE
A64: PS-INV218061 | B64: 13128 | C64: Gordon Food Service - Shepherdsville | D64: 46167 | E64: S-ORD218061 | F64: 21452.48 | G64: NR-BRHL-FG | H64: 1 | I64: 46167 | J64: 46167 | K64: RT 21 | L64: =FALSE() -> FALSE | M64: =FALSE() -> FALSE | N64: =FALSE() -> FALSE
A65: PS-INV217295 | B65: X10540-3 | C65: PFG Pittsburgh PA | D65: 46167 | E65: S-ORD217295 | F65: 30850.4 | G65: NR-BRHL-FG | H65: 1 | I65: 46167 | J65: 46167 | K65: RT 21 | L65: =FALSE() -> FALSE | M65: =FALSE() -> FALSE | N65: =FALSE() -> FALSE
A66: PS-INV218249 | B66: 20334 | C66: Sysco Atlanta | D66: 46164 | E66: S-ORD218249 | F66: 13426.16 | G66: NR-BRHL-FG | H66: 2 | I66: 46164 | J66: 46164 | K66: RT 21 | L66: =TRUE() -> TRUE | M66: =FALSE() -> FALSE | N66: =FALSE() -> FALSE
A67: PS-INV218050 | B67: 13128 | C67: Gordon Food Service - Shepherdsville | D67: 46164 | E67: S-ORD218050 | F67: 31762.08 | G67: NR-BRHL-FG | H67: 2 | I67: 46164 | J67: 46164 | K67: RT 21 | L67: =FALSE() -> FALSE | M67: =FALSE() -> FALSE | N67: =FALSE() -> FALSE
A68: PS-INV218761 | B68: 10540-03 | C68: PFG Louisville TN | D68: 46163 | E68: S-ORD218761 | F68: 23678.24 | G68: NR-BRHL-FG | H68: 2 | I68: 46163 | J68: 46163 | K68: RT 21 | L68: =FALSE() -> FALSE | M68: =FALSE() -> FALSE | N68: =FALSE() -> FALSE
A69: PS-INV218755 | B69: 11005 | C69: Dot Foods Inc. | D69: 46163 | E69: S-ORD218755 | F69: 32083.2 | G69: NR-BRHL-FG | H69: 2 | I69: 46164 | J69: 46164 | K69: RT 21 | L69: =FALSE() -> FALSE | M69: =FALSE() -> FALSE | N69: =FALSE() -> FALSE
A70: PS-INV218753 | B70: 10899 | C70: Wood Fruitticher Grocery Co. | D70: 46163 | E70: S-ORD218753 | F70: 27870.88 | G70: NR-BRHL-FG | H70: 2 | I70: 46163 | J70: 46163 | K70: RT 21 | L70: =TRUE() -> TRUE | M70: =FALSE() -> FALSE | N70: =FALSE() -> FALSE
A71: PS-INV218268 | B71: 10719-2 | C71: US Foods - Fairburn | D71: 46163 | E71: S-ORD218268 | F71: 15747.32 | G71: NR-BRHL-FG | H71: 2 | I71: 46163 | J71: 46163 | K71: RT 21 | L71: =FALSE() -> FALSE | M71: =FALSE() -> FALSE | N71: =FALSE() -> FALSE
A72: PS-INV217674 | B72: 12431 | C72: Ben E Keith - New Brockton | D72: 46163 | E72: S-ORD217674 | F72: 20309.65 | G72: NR-BRHL-FG | H72: 4 | I72: 46163 | J72: 46163 | K72: RT 21 | L72: =FALSE() -> FALSE | M72: =FALSE() -> FALSE | N72: =FALSE() -> FALSE
A73: PS-INV218707 | B73: 12358 | C73: PFG Powell GA | D73: 46162 | E73: S-ORD218707 | F73: 12109.6 | G73: NR-BRHL-FG | H73: 3 | I73: 46162 | J73: 46162 | K73: RT 21 | L73: =FALSE() -> FALSE | M73: =FALSE() -> FALSE | N73: =FALSE() -> FALSE
A74: PS-INV218053 | B74: 10719-4 | C74: US Foods - Columbia/Lexington | D74: 46162 | E74: S-ORD218053 | F74: 10722.36 | G74: NR-BRHL-FG | H74: 6 | I74: 46162 | J74: 46162 | K74: RT 21 | L74: =FALSE() -> FALSE | M74: =FALSE() -> FALSE | N74: =FALSE() -> FALSE
A75: PS-INV216519 | B75: 12988 | C75: Sysco Norman OK | D75: 46162 | E75: S-ORD216519 | F75: 32816 | G75: NR-BRHL-FG | H75: 6 | I75: 46162 | J75: 46162 | K75: RT 21 | L75: =TRUE() -> TRUE | M75: =FALSE() -> FALSE | N75: =FALSE() -> FALSE
A76: PS-INV217231 | B76: 10540-02 | C76: PFG Valdosta GA | D76: 46161 | E76: S-ORD217231 | F76: 3206.4 | G76: NR-BRHL-FG | H76: 8 | I76: 46160 | J76: 46160 | K76: RT 21 | L76: =FALSE() -> FALSE | M76: =FALSE() -> FALSE | N76: =FALSE() -> FALSE
A77: PS-INV215488 | B77: 10711 | C77: Cheney Bros Statesville | D77: 46161 | E77: S-ORD215488 | F77: 11629.12 | G77: NR-BRHL-FG | H77: 6 | I77: 46160 | J77: 46160 | K77: RT 21 | L77: =TRUE() -> TRUE | M77: =FALSE() -> FALSE | N77: =FALSE() -> FALSE
A78: PS-INV214984 | B78: 10719-12 | C78: US Foods - Port Orange | D78: 46161 | E78: S-ORD214984 | F78: 28707.68 | G78: NR-BRHL-FG | H78: 6 | I78: 46160 | J78: 46160 | K78: RT 21 | L78: =FALSE() -> FALSE | M78: =FALSE() -> FALSE | N78: =FALSE() -> FALSE
A79: PS-INV214968 | B79: 10719-6 | C79: US Foods - Alcoa TN. | D79: 46161 | E79: S-ORD214968 | F79: 34521.18 | G79: NR-BRHL-FG | H79: 6 | I79: 46161 | J79: 46161 | K79: RT 21 | L79: =FALSE() -> FALSE | M79: =FALSE() -> FALSE | N79: =FALSE() -> FALSE
A80: PS-INV220297 | B80: 11394 | C80: La Cosecha Food Service | D80: 46157 | E80: S-ORD220297 | F80: 1446.02 | G80: NR-BRHL-FG | H80: 1 | I80: 46170 | J80: 46170 | K80: RT 21 | L80: =TRUE() -> TRUE | M80: =FALSE() -> FALSE | N80: =FALSE() -> FALSE
A81: PS-INV216842 | B81: 10540-03 | C81: PFG Louisville TN | D81: 46156 | E81: S-ORD216842 | F81: 20019.04 | G81: NR-BRHL-FG | H81: 4 | I81: 46156 | J81: 46156 | K81: RT 21 | L81: =FALSE() -> FALSE | M81: =FALSE() -> FALSE | N81: =FALSE() -> FALSE
A82: PS-INV216537 | B82: 10540-01 | C82: PFG Johnson City TN | D82: 46156 | E82: S-ORD216537 | F82: 12190.28 | G82: NR-BRHL-FG | H82: 4 | I82: 46156 | J82: 46156 | K82: RT 21 | L82: =FALSE() -> FALSE | M82: =FALSE() -> FALSE | N82: =FALSE() -> FALSE
A83: PS-INV215225 | B83: 20334 | C83: Sysco Atlanta | D83: 46156 | E83: S-ORD215225 | F83: 11026.92 | G83: NR-BRHL-FG | H83: 2 | I83: 46156 | J83: 46156 | K83: RT 21 | L83: =TRUE() -> TRUE | M83: =FALSE() -> FALSE | N83: =FALSE() -> FALSE
A84: PS-INV213779 | B84: 12988 | C84: Sysco Norman OK | D84: 46156 | E84: S-ORD213779 | F84: 24822 | G84: NR-BRHL-FG | H84: 3 | I84: 46156 | J84: 46156 | K84: RT 21 | L84: =TRUE() -> TRUE | M84: =FALSE() -> FALSE | N84: =FALSE() -> FALSE
A85: PS-INV215573 | B85: 11394 | C85: La Cosecha Food Service | D85: 46155 | E85: S-ORD215573 | F85: 1586.6 | G85: NR-BRHL-FG | H85: 2 | I85: 46155 | J85: 46155 | K85: RT 21 | L85: =TRUE() -> TRUE | M85: =FALSE() -> FALSE | N85: =FALSE() -> FALSE
A86: PS-INV214979 | B86: 13128 | C86: Gordon Food Service - Shepherdsville | D86: 46154 | E86: S-ORD214979 | F86: 32237.12 | G86: NR-BRHL-FG | H86: 3 | I86: 46154 | J86: 46154 | K86: RT 21 | L86: =TRUE() -> TRUE | M86: =FALSE() -> FALSE | N86: =FALSE() -> FALSE
A87: PS-INV214717 | B87: 12314 | C87: Gordon Food Services - Concord | D87: 46154 | E87: S-ORD214717 | F87: 12350.06 | G87: NR-BRHL-FG | H87: 3 | I87: 46154 | J87: 46154 | K87: RT 21 | L87: =TRUE() -> TRUE | M87: =FALSE() -> FALSE | N87: =FALSE() -> FALSE
A88: PS-INV213725 | B88: 10719-2 | C88: US Foods - Fairburn | D88: 46154 | E88: S-ORD213725 | F88: 13933.7 | G88: NR-BRHL-FG | H88: 4 | I88: 46154 | J88: 46154 | K88: RT 21 | L88: =FALSE() -> FALSE | M88: =FALSE() -> FALSE | N88: =FALSE() -> FALSE
A89: PS-INV212804 | B89: 10138-5 | C89: Costco PriceSmart Export | D89: 46154 | E89: S-ORD212804 | F89: 25200 | G89: NR-BRHL-FG | H89: 6 | I89: 46154 | J89: 46154 | K89: RT 21 | L89: =TRUE() -> TRUE | M89: =FALSE() -> FALSE | N89: =FALSE() -> FALSE
A90: PS-INV213752 | B90: Z10700 | C90: Sysco-Charlotte | D90: 46153 | E90: S-ORD213752 | F90: 22721.14 | G90: NR-BRHL-FG | H90: 2 | I90: 46153 | J90: 46153 | K90: RT 21 | L90: =TRUE() -> TRUE | M90: =FALSE() -> FALSE | N90: =FALSE() -> FALSE
A91: PS-INV210818 | B91: 10719-13 | C91: US Foods - Montgomery | D91: 46153 | E91: S-ORD210818 | F91: 22221.92 | G91: NR-BRHL-FG | H91: 2 | I91: 46153 | J91: 46153 | K91: RT 21 | L91: =FALSE() -> FALSE | M91: =FALSE() -> FALSE | N91: =FALSE() -> FALSE
A92: PS-INV216512 | B92: Z11655 | C92: PFG Hickory NC | D92: 46150 | E92: S-ORD216512 | F92: 1232 | G92: NR-BRHL-FG | H92: 1 | I92: 46150 | J92: 46150 | K92: RT 21 | L92: =FALSE() -> FALSE | M92: =FALSE() -> FALSE | N92: =FALSE() -> FALSE
A93: PS-INV213776 | B93: 20334 | C93: Sysco Atlanta | D93: 46149 | E93: S-ORD213776 | F93: 11468.48 | G93: NR-BRHL-FG | H93: 1 | I93: 46149 | J93: 46149 | K93: RT 21 | L93: =TRUE() -> TRUE | M93: =FALSE() -> FALSE | N93: =FALSE() -> FALSE
A94: PS-INV213718 | B94: 10540-03 | C94: PFG Louisville TN | D94: 46149 | E94: S-ORD213718 | F94: 27135.16 | G94: NR-BRHL-FG | H94: 2 | I94: 46149 | J94: 46149 | K94: RT 21 | L94: =FALSE() -> FALSE | M94: =FALSE() -> FALSE | N94: =FALSE() -> FALSE
A95: PS-INV211906 | B95: 12989 | C95: Sysco Little Rock Arkansas | D95: 46149 | E95: S-ORD211906 | F95: 10694.6 | G95: NR-BRHL-FG | H95: 1 | I95: 46149 | J95: 46149 | K95: RT 21 | L95: =TRUE() -> TRUE | M95: =FALSE() -> FALSE | N95: =FALSE() -> FALSE
A96: PS-INV213761 | B96: 12438 | C96: SGC Foodservice | D96: 46148 | E96: S-ORD213761 | F96: 28224 | G96: NR-BRHL-FG | H96: 2 | I96: 46148 | J96: 46148 | K96: RT 21 | L96: =TRUE() -> TRUE | M96: =FALSE() -> FALSE | N96: =FALSE() -> FALSE
A97: PS-INV212713 | B97: 10719-4 | C97: US Foods - Columbia/Lexington | D97: 46148 | E97: S-ORD212713 | F97: 13715.5 | G97: NR-BRHL-FG | H97: 3 | I97: 46148 | J97: 46148 | K97: RT 21 | L97: =FALSE() -> FALSE | M97: =FALSE() -> FALSE | N97: =FALSE() -> FALSE
A98: PS-INV211228 | B98: 12988 | C98: Sysco Norman OK | D98: 46148 | E98: S-ORD211228 | F98: 19768 | G98: NR-BRHL-FG | H98: 2 | I98: 46148 | J98: 46148 | K98: RT 21 | L98: =TRUE() -> TRUE | M98: =FALSE() -> FALSE | N98: =FALSE() -> FALSE
A99: PS-INV210832 | B99: 10805 | C99: Sysco Jacksonville | D99: 46148 | E99: S-ORD210832 | F99: 20478.8 | G99: NR-BRHL-FG | H99: 2 | I99: 46149 | J99: 46149 | K99: RT 21 | L99: =TRUE() -> TRUE | M99: =FALSE() -> FALSE | N99: =FALSE() -> FALSE
A100: PS-INV213767 | B100: 10547 | C100: PFG Hale TN | D100: 46147 | E100: S-ORD213767 | F100: 24663 | G100: NR-BRHL-FG | H100: 3 | I100: 46147 | J100: 46147 | K100: RT 21 | L100: =TRUE() -> TRUE | M100: =FALSE() -> FALSE | N100: =FALSE() -> FALSE
A101: PS-INV212693 | B101: 10511 | C101: Sysco Nashville, LLC | D101: 46147 | E101: S-ORD212693 | F101: 25695.84 | G101: NR-BRHL-FG | H101: 4 | I101: 46147 | J101: 46147 | K101: RT 21 | L101: =TRUE() -> TRUE | M101: =FALSE() -> FALSE | N101: =FALSE() -> FALSE
A102: PS-INV210532 | B102: 10719-6 | C102: US Foods - Alcoa TN. | D102: 46147 | E102: S-ORD210532 | F102: 34693.6 | G102: NR-BRHL-FG | H102: 2 | I102: 46147 | J102: 46147 | K102: RT 21 | L102: =FALSE() -> FALSE | M102: =FALSE() -> FALSE | N102: =FALSE() -> FALSE
A103: PS-INV212327 | B103: 13128 | C103: Gordon Food Service - Shepherdsville | D103: 46146 | E103: S-ORD212327 | F103: 33250.88 | G103: NR-BRHL-FG | H103: 2 | I103: 46146 | J103: 46146 | K103: RT 21 | L103: =TRUE() -> TRUE | M103: =FALSE() -> FALSE | N103: =FALSE() -> FALSE
A104: PS-INV210167 | B104: 10719-9 | C104: US Foods -Carolinas/Ft.Mill | D104: 46146 | E104: S-ORD210167 | F104: 21658.52 | G104: NR-BRHL-FG | H104: 2 | I104: 46146 | J104: 46146 | K104: RT 21 | L104: =FALSE() -> FALSE | M104: =FALSE() -> FALSE | N104: =FALSE() -> FALSE
A105: PS-INV209739 | B105: 12707 | C105: PFG Florence SC | D105: 46146 | E105: S-ORD209739 | F105: 7828.8 | G105: NR-BRHL-FG | H105: 1 | I105: 46146 | J105: 46146 | K105: RT 21 | L105: =TRUE() -> TRUE | M105: =FALSE() -> FALSE | N105: =FALSE() -> FALSE
A106: PS-INV211490 | B106: 10540-03 | C106: PFG Louisville TN | D106: 46142 | E106: S-ORD211490 | F106: 30082.96 | G106: NR-BRHL-FG | H106: 2 | I106: 46142 | J106: 46142 | K106: RT 21 | L106: =TRUE() -> TRUE | M106: =FALSE() -> FALSE | N106: =FALSE() -> FALSE
A107: PS-INV211268 | B107: 12431 | C107: Ben E Keith - New Brockton | D107: 46142 | E107: S-ORD211268 | F107: 18425.4 | G107: NR-BRHL-FG | H107: 4 | I107: 46142 | J107: 46142 | K107: RT 21 | L107: =TRUE() -> TRUE | M107: =FALSE() -> FALSE | N107: =FALSE() -> FALSE
A108: PS-INV210810 | B108: 20334 | C108: Sysco Atlanta | D108: 46142 | E108: S-ORD210810 | F108: 10568.97 | G108: NR-BRHL-FG | H108: 1 | I108: 46142 | J108: 46142 | K108: RT 21 | L108: =TRUE() -> TRUE | M108: =FALSE() -> FALSE | N108: =FALSE() -> FALSE
A109: PS-INV209045 | B109: 12988 | C109: Sysco Norman OK | D109: 46142 | E109: S-ORD209045 | F109: 24472 | G109: NR-BRHL-FG | H109: 2 | I109: 46142 | J109: 46142 | K109: RT 21 | L109: =TRUE() -> TRUE | M109: =FALSE() -> FALSE | N109: =FALSE() -> FALSE
A110: PS-INV212205 | B110: 10899 | C110: Wood Fruitticher Grocery Co. | D110: 46141 | E110: S-ORD212205 | F110: 27053.04 | G110: NR-BRHL-FG | H110: 2 | I110: 46141 | J110: 46141 | K110: RT 21 | L110: =TRUE() -> TRUE | M110: =FALSE() -> FALSE | N110: =FALSE() -> FALSE
A111: PS-INV210816 | B111: 12358 | C111: PFG Powell GA | D111: 46141 | E111: S-ORD210816 | F111: 11829.6 | G111: NR-BRHL-FG | H111: 1 | I111: 46141 | J111: 46141 | K111: RT 21 | L111: =FALSE() -> FALSE | M111: =FALSE() -> FALSE | N111: =FALSE() -> FALSE
A112: PS-INV214731 | B112: 12988 | C112: Sysco Norman OK | D112: 46140 | E112: S-ORD214731 | F112: 2016 | G112: NR-BRHL-FG | H112: 5 | I112: 46140 | J112: 46140 | K112: RT 21 | L112: =FALSE() -> FALSE | M112: =FALSE() -> FALSE | N112: =FALSE() -> FALSE
A113: PS-INV208059 | B113: 13092 | C113: Sysco WEST COAST | D113: 46140 | E113: S-ORD208059 | F113: 16154.6 | G113: NR-BRHL-FG | H113: 2 | I113: 46140 | J113: 46140 | K113: RT 21 | L113: =TRUE() -> TRUE | M113: =FALSE() -> FALSE | N113: =FALSE() -> FALSE
A114: PS-INV204215 | B114: 13244 | C114: PFG Cedar Rapids | D114: 46140 | E114: S-ORD204215 | F114: 35103.6 | G114: NR-BRHL-FG | H114: 6 | I114: 46140 | J114: 46140 | K114: RT 21 | L114: =TRUE() -> TRUE | M114: =FALSE() -> FALSE | N114: =FALSE() -> FALSE
A115: PS-INV209742 | B115: 10899 | C115: Wood Fruitticher Grocery Co. | D115: 46139 | E115: S-ORD209742 | F115: 27570.04 | G115: NR-BRHL-FG | H115: 2 | I115: 46139 | J115: 46139 | K115: RT 21 | L115: =TRUE() -> TRUE | M115: =FALSE() -> FALSE | N115: =FALSE() -> FALSE
A116: PS-INV209734 | B116: 10540-02 | C116: PFG Valdosta GA | D116: 46139 | E116: S-ORD209734 | F116: 10668.4 | G116: NR-BRHL-FG | H116: 2 | I116: 46139 | J116: 46139 | K116: RT 21 | L116: =TRUE() -> TRUE | M116: =FALSE() -> FALSE | N116: =FALSE() -> FALSE
A117: PS-INV203842 | B117: 20334 | C117: Sysco Atlanta | D117: 46136 | E117: S-ORD203842 | F117: 15403.24 | G117: NR-BRHL-FG | H117: 1 | I117: 46136 | J117: 46136 | K117: RT 21 | L117: =TRUE() -> TRUE | M117: =FALSE() -> FALSE | N117: =FALSE() -> FALSE
A118: PS-INV209038 | B118: 10540-03 | C118: PFG Louisville TN | D118: 46135 | E118: S-ORD209038 | F118: 28252.04 | G118: NR-BRHL-FG | H118: 2 | I118: 46135 | J118: 46135 | K118: RT 21 | L118: =TRUE() -> TRUE | M118: =FALSE() -> FALSE | N118: =FALSE() -> FALSE
A119: PS-INV208814 | B119: 11394 | C119: La Cosecha Food Service | D119: 46135 | E119: S-ORD208814 | F119: 1973.6 | G119: NR-BRHL-FG | H119: 1 | I119: 46135 | J119: 46135 | K119: RT 21 | L119: =TRUE() -> TRUE | M119: =FALSE() -> FALSE | N119: =FALSE() -> FALSE
A120: PS-INV208428 | B120: 20334 | C120: Sysco Atlanta | D120: 46135 | E120: S-ORD208428 | F120: 12612.88 | G120: NR-BRHL-FG | H120: 1 | I120: 46135 | J120: 46135 | K120: RT 21 | L120: =TRUE() -> TRUE | M120: =FALSE() -> FALSE | N120: =FALSE() -> FALSE
A121: PS-INV207349 | B121: 10719-2 | C121: US Foods - Fairburn | D121: 46135 | E121: S-ORD207349 | F121: 16007.27 | G121: NR-BRHL-FG | H121: 2 | I121: 46135 | J121: 46135 | K121: RT 21 | L121: =TRUE() -> TRUE | M121: =FALSE() -> FALSE | N121: =FALSE() -> FALSE
A122: PS-INV208406 | B122: 10719-4 | C122: US Foods - Columbia/Lexington | D122: 46134 | E122: S-ORD208406 | F122: 7433.44 | G122: NR-BRHL-FG | H122: 4 | I122: 46134 | J122: 46134 | K122: RT 21 | L122: =FALSE() -> FALSE | M122: =FALSE() -> FALSE | N122: =FALSE() -> FALSE
A123: PS-INV208064 | B123: 10511 | C123: Sysco Nashville, LLC | D123: 46134 | E123: S-ORD208064 | F123: 20203.16 | G123: NR-BRHL-FG | H123: 4 | I123: 46134 | J123: 46134 | K123: RT 21 | L123: =TRUE() -> TRUE | M123: =FALSE() -> FALSE | N123: =FALSE() -> FALSE
A124: PS-INV207718 | B124: 10805 | C124: Sysco Jacksonville | D124: 46134 | E124: S-ORD207718 | F124: 21253.6 | G124: NR-BRHL-FG | H124: 2 | I124: 46134 | J124: 46134 | K124: RT 21 | L124: =TRUE() -> TRUE | M124: =FALSE() -> FALSE | N124: =FALSE() -> FALSE
A125: PS-INV207344 | B125: 12988 | C125: Sysco Norman OK | D125: 46134 | E125: S-ORD207344 | F125: 15456 | G125: NR-BRHL-FG | H125: 4 | I125: 46134 | J125: 46134 | K125: RT 21 | L125: =TRUE() -> TRUE | M125: =FALSE() -> FALSE | N125: =FALSE() -> FALSE
A126: PS-INV205928 | B126: 10547 | C126: PFG Hale | D126: 46134 | E126: S-ORD205928 | F126: 24502.6 | G126: NR-BRHL-FG | H126: 3 | I126: 46134 | J126: 46134 | K126: RT 21 | L126: =TRUE() -> TRUE | M126: =FALSE() -> FALSE | N126: =FALSE() -> FALSE
...

Sheet Posted Sales Invoice Lines
A1: Document No. | B1: Sell-to Customer No. | C1: Sell-to Customer Name | D1: Type | E1: No. | F1: Description | G1: Posting Date | H1: Gen. Bus. Posting Group | I1: Gen. Prod. Posting Group | J1: Pc Code | K1: Dept Code | L1: Quantity | M1: Unit of Measure Code | N1: Unit Price Excl. Tax | O1: Amount | P1: Amount Including Tax | Q1: Line Discount %
A2: PS-INV173271 | B2: 10719-6 | C2: US Foods - Alcoa TN. | D2: Item | E2: F53094 | F2: Cs. 6" Italian 12-6pks | G2: 46027 | I2: FG-DIST | J2: EBC | L2: 28 | M2: EA | N2: 35 | O2: 980 | P2: 980 | Q2: 0
A3: PS-INV173271 | B3: 10719-6 | C3: US Foods - Alcoa TN. | D3: Item | E3: F51136 | F3: Cs. Texas Toast 1" 12lvs | G3: 46027 | I3: FG-DIST | J3: EBC | L3: 84 | M3: EA | N3: 40.12 | O3: 3370.08 | P3: 3370.08 | Q3: 0
A4: PS-INV173271 | B4: 10719-6 | C4: US Foods - Alcoa TN. | D4: Item | E4: F51004 | F4: Cs. Rye 5/8" 8lvs | G4: 46027 | I4: FG-DIST | J4: EBC | L4: 8 | M4: EA | N4: 42.03 | O4: 336.24 | P4: 336.24 | Q4: 0
A5: PS-INV173271 | B5: 10719-6 | C5: US Foods - Alcoa TN. | D5: Item | E5: F53025 | F5: Cs. Sesame Challah Kaiser 8-12pk | G5: 46027 | I5: FG-DIST | J5: EBC | L5: 308 | M5: EA | N5: 39 | O5: 12012 | P5: 12012 | Q5: 0
A6: PS-INV173271 | B6: 10719-6 | C6: US Foods - Alcoa TN. | D6: Item | E6: F53087 | F6: Cs. 3.5" Challah Bun 8-12 pk | G6: 46027 | I6: FG-DIST | J6: EBC | L6: 28 | M6: EA | N6: 36.24 | O6: 1014.72 | P6: 1014.72 | Q6: 0
A7: PS-INV173271 | B7: 10719-6 | C7: US Foods - Alcoa TN. | D7: Item | E7: F51066 | F7: Cs. Honey Wheat 3/4" 8lvs | G7: 46027 | I7: FG-DIST | J7: EBC | L7: 14 | M7: EA | N7: 35.21 | O7: 492.94 | P7: 492.94 | Q7: 0
A8: PS-INV173271 | B8: 10719-6 | C8: US Foods - Alcoa TN. | D8: Item | E8: F53001 | F8: Cs. 4" Brioche Bun 8-12pk | G8: 46027 | I8: FG-DIST | J8: EBC | L8: 140 | M8: EA | N8: 45.49 | O8: 6368.6 | P8: 6368.6 | Q8: 0
A9: PS-INV173271 | B9: 10719-6 | C9: US Foods - Alcoa TN. | D9: Item | E9: F530501 | F9: Cs. 4.5" Challah Kaiser 6-12pk | G9: 46027 | I9: FG-DIST | J9: EBC | L9: 28 | M9: EA | N9: 37.02 | O9: 1036.56 | P9: 1036.56 | Q9: 0
A10: PS-INV173271 | B10: 10719-6 | C10: US Foods - Alcoa TN. | D10: Item | E10: F51084 | F10: Cs. Wheatberry Hearth | G10: 46027 | I10: FG-DIST | J10: EBC | L10: 4 | M10: EA | N10: 52.47 | O10: 209.88 | P10: 209.88 | Q10: 0
A11: PS-INV173271 | B11: 10719-6 | C11: US Foods - Alcoa TN. | D11: Item | E11: F51024 | F11: Cs. Marble Rye 5/8" 8lvs | G11: 46027 | I11: FG-DIST | J11: EBC | L11: 4 | M11: EA | N11: 54 | O11: 216 | P11: 216 | Q11: 0
A12: PS-INV173271 | B12: 10719-6 | C12: US Foods - Alcoa TN. | D12: Item | E12: F51034 | F12: Cs. Sour Dough Hearth 5/8" 8lvs | G12: 46027 | I12: FG-DIST | J12: EBC | L12: 8 | M12: EA | N12: 43.2 | O12: 345.6 | P12: 345.6 | Q12: 0
A13: PS-INV173271 | B13: 10719-6 | C13: US Foods - Alcoa TN. | D13: Item | E13: F51157 | F13: Cs. Challah Hearth 7/8" 8lvs | G13: 46027 | I13: FG-DIST | J13: EBC | L13: 28 | M13: EA | N13: 44.15 | O13: 1236.2 | P13: 1236.2 | Q13: 0
... A86: PS-INV178030 | B86: 12989 | C86: Sysco Little Rock Arkansas | D86: Item | E86: F53115 | F86: Cs. 7" French Unsliced 12-6pk | G86: 46037 | I86: FG-DIST | J86: EBC | L86: 224 | M86: EA | N86: 35 | O86: 7840 | P86: 7840 | Q86: 0
A87: PS-INV178033 | B87: 13092 | C87: Sysco WEST COAST | D87: Item | E87: F51137 | F87: Cs. Texas Toast 3/4" 12lvs | G87: 46035 | H87: DOMESTIC | I87: FG-DIST | J87: EBC | L87: 336 | M87: EA | N87: 35 | O87: 11760 | P87: 11760 | Q87: 0
A88: PS-INV178033 | B88: 13092 | C88: Sysco WEST COAST | D88: Item | E88: F530491 | F88: Cs. 4.5 Brioche Bun 6-12pk | G88: 46035 | H88: DOMESTIC | I88: FG-DIST | J88: EBC | L88: 112 | M88: EA | N88: 39.65 | O88: 4440.8 | P88: 4440.8 | Q88: 0
A89: PS-INV178270 | B89: 10540-02 | C89: PFG Valdosta GA | D89: Item | E89: F53001 | F89: Cs. 4" Brioche Bun 8-12pk | G89: 46036 | I89: FG-DIST | J89: EBC | L89: 40 | M89: EA | N89: 42.6 | O89: 1704 | P89: 1704 | Q89: 0
A90: PS-INV178270 | B90: 10540-02 | C90: PFG Valdosta GA | D90: Item | E90: F54301 | F90: Cs. Potato Roll Sliced 12-16pk | G90: 46036 | I90: FG-DIST | J90: EBC | L90: 36 | M90: EA | N90: 41.15 | O90: 1481.4 | P90: 1481.4 | Q90: 0
A91: PS-INV178270 | B91: 10540-02 | C91: PFG Valdosta GA | D91: Item | E91: F51000 | F91: Cs. Rye Bread 8lvs | G91: 46036 | I91: FG-DIST | J91: EBC | L91: 4 | M91: EA | N91: 41.6 | O91: 166.4 | P91: 166.4 | Q91: 0
A92: PS-INV178288 | B92: 11394 | C92: La Cosecha Food Service | D92: Item | E92: F53003 | F92: Cs. 4" Unseeded Challah Bun 8-12pk | G92: 46036 | I92: FG-DIST | J92: EBC | L92: 30 | M92: EA | N92: 30.32 | O92: 909.6 | P92: 909.6 | Q92: 0
A93: PS-INV178288 | B93: 11394 | C93: La Cosecha Food Service | D93: Item | E93: F530401 | F93: Cs. 4.5" Sesame 6-12pk | G93: 46036 | I93: FG-DIST | J93: EBC | L93: 30 | M93: EA | N93: 34.18 | O93: 1025.4 | P93: 1025.4 | Q93: 0
A94: PS-INV178335 | B94: 10805 | C94: Sysco Jacksonville | D94: Item | E94: F53100 | F94: Cs. Hot Dog pl/sl 12-8pk | G94: 46037 | I94: FG-DIST | J94: EBC | L94: 4 | M94: EA | N94: 36.6 | O94: 146.4 | P94: 146.4 | Q94: 0
A95: PS-INV178335 | B95: 10805 | C95: Sysco Jacksonville | D95: Item | E95: F53001 | F95: Cs. 4" Brioche Bun 8-12pk | G95: 46037 | I95: FG-DIST | J95: EBC | L95: 28 | M95: EA | N95: 50.6 | O95: 1416.8 | P95: 1416.8 | Q95: 0
A96: PS-INV178335 | B96: 10805 | C96: Sysco Jacksonville | D96: Item | E96: F53003 | F96: Cs. 4" Unseeded Challah Bun 8-12pk | G96: 46037 | I96: FG-DIST | J96: EBC | L96: 252 | M96: EA | N96: 40.8 | O96: 10281.6 | P96: 10281.6 | Q96: 0
A97: PS-INV178335 | B97: 10805 | C97: Sysco Jacksonville | D97: Item | E97: F51137 | F97: Cs. Texas Toast 3/4" 12lvs | G97: 46037 | I97: FG-DIST | J97: EBC | L97: 140 | M97: EA | N97: 39.9 | O97: 5586 | P97: 5586 | Q97: 0
A98: PS-INV178335 | B98: 10805 | C98: Sysco Jacksonville | D98: Item | E98: F56251 | F98: Cs. Challah Sliders Sliced 18-12pks | G98: 46037 | I98: FG-DIST | J98: EBC | L98: 28 | M98: EA | N98: 42.35 | O98: 1185.8 | P98: 1185.8 | Q98: 0
A99: PS-INV178998 | B99: 10899 | C99: Wood Fruitticher Grocery Co. | D99: Item | E99: F54301 | F99: Cs. Potato Roll Sliced 12-16pk | G99: 46027 | I99: FG-DIST | J99: EBC | L99: 12 | M99: EA | N99: 40.1 | O99: 481.2 | P99: 481.2 | Q99: 0
A100: PS-INV178998 | B100: 10899 | C100: Wood Fruitticher Grocery Co. | D100: Item | E100: F53115 | F100: Cs. 7" French Unsliced 12-6pk | G100: 46027 | I100: FG-DIST | J100: EBC | L100: 12 | M100: EA | N100: 28.88 | O100: 346.56 | P100: 346.56 | Q100: 0
... A116: PS-INV179010 | B116: 20334 | C116: Sysco Atlanta | D116: Item | E116: F53140 | F116: Cs. Knuckies 8" White 12-6pk | G116: 46037 | I116: FG-DIST | J116: EBC | L116: 20 | M116: EA | N116: 41 | O116: 820 | P116: 820 | Q116: 0
A117: PS-INV179035 | B117: 13128 | C117: Gordon Food Service - Shepherdsville | D117: Item | E117: F51084 | F117: Cs. Wheatberry Hearth | G117: 46037 | H117: DOMESTIC | I117: FG-DIST | J117: EBC | L117: 48 | M117: EA | N117: 33.3 | O117: 1598.4 | P117: 1598.4 | Q117: 0
A118: PS-INV179035 | B118: 13128 | C118: Gordon Food Service - Shepherdsville | D118: Item | E118: F53001 | F118: Cs. 4" Brioche Bun 8-12pk | G118: 46037 | H118: DOMESTIC | I118: FG-DIST | J118: EBC | L118: 256 | M118: EA | N118: 36.82 | O118: 9425.92 | P118: 9425.92 | Q118: 0
A119: PS-INV179035 | B119: 13128 | C119: Gordon Food Service - Shepherdsville | D119: Item | E119: F51114 | F119: Cs. Old Fashioned Hearth 5/8" 8lvs | G119: 46037 | H119: DOMESTIC | I119: FG-DIST | J119: EBC | L119: 112 | M119: EA | N119: 39.7 | O119: 4446.4 | P119: 4446.4 | Q119: 0
A120: PS-INV179035 | B120: 13128 | C120: Gordon Food Service - Shepherdsville | D120: Item | E120: F56251 | F120: Cs. Challah Sliders Sliced 18-12pks | G120: 46037 | H120: DOMESTIC | I120: FG-DIST | J120: EBC | L120: 400 | M120: EA | N120: 39.7 | O120: 15880 | P120: 15880 | Q120: 0
A121: PS-INV179062 | B121: 10719-2 | C121: US Foods - Fairburn | D121: Item | E121: F53005 | F121: Cs. 4" Gourmet PDS Bun 8-12pk | G121: 46041 | I121: FG-DIST | J121: EBC | L121: 52 | M121: EA | N121: 40.11 | O121: 2085.72 | P121: 2085.72 | Q121: 0
A122: PS-INV179062 | B122: 10719-2 | C122: US Foods - Fairburn | D122: Item | E122: F56560 | F122: Gluten Free 3.5" Hamburger 36ct | G122: 46041 | I122: FG-DIST | J122: EBC | L122: 12 | M122: EA | N122: 48.57 | O122: 582.84 | P122: 582.84 | Q122: 0
A123: PS-INV179062 | B123: 10719-2 | C123: US Foods - Fairburn | D123: Item | E123: F53010 | F123: Cs. Onion Roll 8-12pk | G123: 46041 | I123: FG-DIST | J123: EBC | L123: 32 | M123: EA | N123: 40.85 | O123: 1307.2 | P123: 1307.2 | Q123: 0
A124: PS-INV179062 | B124: 10719-2 | C124: US Foods - Fairburn | D124: Item | E124: F53122 | F124: Cs. 8" Italian Hinged 12-6pk | G124: 46041 | I124: FG-DIST | J124: EBC | L124: 116 | M124: EA | N124: 40.9 | O124: 4744.4 | P124: 4744.4 | Q124: 0
A125: PS-INV179062 | B125: 10719-2 | C125: US Foods - Fairburn | D125: Item | E125: F53003 | F125: Cs. 4" Unseeded Challah Bun 8-12pk | G125: 46041 | I125: FG-DIST | J125: EBC | L125: 72 | M125: EA | N125: 38.08 | O125: 2741.76 | P125: 2741.76 | Q125: 0
A126: PS-INV179062 | B126: 10719-2 | C126: US Foods - Fairburn | D126: Item | E126: F53024 | F126: Cs. 4" Challah Kaiser 8-12pk | G126: 46041 | I126: FG-DIST | J126: EBC | L126: 60 | M126: EA | N126: 40.22 | O126: 2413.2 | P126: 2413.2 | Q126: 0
A127: PS-INV179701 | B127: 10540-03 | C127: PFG Louisville TN | D127: Item | E127: F530501 | F127: Cs. 4.5" Challah Kaiser 6-12pk | G127: 46037 | I127: FG-DIST | J127: EBC | L127: 28 | M127: EA | N127: 38.3 | O127: 1072.4 | P127: 1072.4 | Q127: 0
A128: PS-INV179701 | B128: 10540-03 | C128: PFG Louisville TN | D128: Item | E128: F51137 | F128: Cs. Texas Toast 3/4" 12lvs | G128: 46037 | I128: FG-DIST | J128: EBC | L128: 0 | M128: EA | N128: 40.62 | O128: 0 | P128: 0 | Q128: 0
A129: PS-INV179701 | B129: 10540-03 | C129: PFG Louisville TN | D129: Item | E129: F53091 | F129: Cs. 6" Hoagie Slab Cut | G129: 46037 | I129: FG-DIST | J129: EBC | L129: 28 | M129: EA | N129: 35 | O129: 980 | P129: 980 | Q129: 0
A130: PS-INV179701 | B130: 10540-03 | C130: PFG Louisville TN | D130: Item | E130: F530421 | F130: Cs. 4.5" Challah Buns 6-12pk. | G130: 46037 | I130: FG-DIST | J130: EBC | L130: 84 | M130: EA | N130: 38.3 | O130: 3217.2 | P130: 3217.2 | Q130: 0
A131: PS-INV179701 | B131: 10540-03 | C131: PFG Louisville TN | D131: Item | E131: F51080 | F131: Cs. Wheatberry Hearth 1/2" 8lvs | G131: 46037 | I131: FG-DIST | J131: EBC | L131: 28 | M131: EA | N131: 49 | O131: 1372 | P131: 1372 | Q131: 0
A132: PS-INV179701 | B132: 10540-03 | C132: PFG Louisville TN | D132: Item | E132: F51030 | F132: Cs. Sour Dough Hearth 8lvs | G132: 46037 | I132: FG-DIST | J132: EBC | L132: 0 | M132: EA | N132: 43.82 | O132: 0 | P132: 0 | Q132: 0
... A185: PS-INV180652 | B185: 20334 | C185: Sysco Atlanta | D185: Item | E185: F53033 | F185: Cs. 4" Parker House 8-12pk | G185: 46044 | I185: FG-DIST | J185: EBC | L185: 56 | M185: EA | N185: 39.53 | O185: 2213.68 | P185: 2213.68 | Q185: 0
A186: PS-INV180718 | B186: 13128 | C186: Gordon Food Service - Shepherdsville | D186: Item | E186: F51084 | F186: Cs. Wheatberry Hearth | G186: 46043 | H186: DOMESTIC | I186: FG-DIST | J186: EBC | L186: 80 | M186: EA | N186: 33.3 | O186: 2664 | P186: 2664 | Q186: 0
A187: PS-INV180718 | B187: 13128 | C187: Gordon Food Service - Shepherdsville | D187: Item | E187: F53001 | F187: Cs. 4" Brioche Bun 8-12pk | G187: 46043 | H187: DOMESTIC | I187: FG-DIST | J187: EBC | L187: 336 | M187: EA | N187: 36.82 | O187: 12371.52 | P187: 12371.52 | Q187: 0
A188: PS-INV180718 | B188: 13128 | C188: Gordon Food Service - Shepherdsville | D188: Item | E188: F51114 | F188: Cs. Old Fashioned Hearth 5/8" 8lvs | G188: 46043 | H188: DOMESTIC | I188: FG-DIST | J188: EBC | L188: 112 | M188: EA | N188: 39.7 | O188: 4446.4 | P188: 4446.4 | Q188: 0
A189: PS-INV180718 | B189: 13128 | C189: Gordon Food Service - Shepherdsville | D189: Item | E189: F56251 | F189: Cs. Challah Sliders Sliced 18-12pks | G189: 46043 | H189: DOMESTIC | I189: FG-DIST | J189: EBC | L189: 320 | M189: EA | N189: 39.7 | O189: 12704 | P189: 12704 | Q189: 0
A190: PS-INV180754 | B190: 10719-13 | C190: US Foods - Montgomery | D190: Item | E190: F53005 | F190: Cs. 4" Gourmet PDS Bun 8-12pk | G190: 46050 | I190: FG-DIST | J190: EBC | L190: 224 | M190: EA | N190: 37 | O190: 8288 | P190: 8288 | Q190: 0
A191: PS-INV180754 | B191: 10719-13 | C191: US Foods - Montgomery | D191: Item | E191: F53010 | F191: Cs. Onion Roll 8-12pk | G191: 46050 | I191: FG-DIST | J191: EBC | L191: 28 | M191: EA | N191: 42 | O191: 1176 | P191: 1176 | Q191: 0
A192: PS-INV180754 | B192: 10719-13 | C192: US Foods - Montgomery | D192: Item | E192: F53001 | F192: Cs. 4" Brioche Bun 8-12pk | G192: 46050 | I192: FG-DIST | J192: EBC | L192: 112 | M192: EA | N192: 42 | O192: 4704 | P192: 4704 | Q192: 0
A193: PS-INV180754 | B193: 10719-13 | C193: US Foods - Montgomery | D193: Item | E193: F53003 | F193: Cs. 4" Unseeded Challah Bun 8-12pk | G193: 46050 | I193: FG-DIST | J193: EBC | L193: 196 | M193: EA | N193: 38.08 | O193: 7463.68 | P193: 7463.68 | Q193: 0
A194: PS-INV180999 | B194: 10155-45 | C194: Hammer and Spoon MTWTHF | D194: Item | E194: F56251 | F194: Cs. Challah Sliders Sliced 18-12pks | G194: 46031 | H194: DOMESTIC | I194: FG-DIST | J194: EBC | L194: 0 | M194: EA | N194: 0 | O194: 0 | P194: 0 | Q194: 0
A195: PS-INV180999 | B195: 10155-45 | C195: Hammer and Spoon MTWTHF | D195: Item | E195: F56560 | F195: Gluten Free 3.5" Hamburger 36ct | G195: 46031 | H195: DOMESTIC | I195: FG-DIST | J195: EBC | L195: 0 | M195: EA | N195: 0 | O195: 0 | P195: 0 | Q195: 0
A196: PS-INV180999 | B196: 10155-45 | C196: Hammer and Spoon MTWTHF | D196: Item | E196: F56255 | F196: Cs. English Muffin 30-6pk | G196: 46031 | H196: DOMESTIC | I196: FG-DIST | J196: EBC | L196: 0 | M196: EA | N196: 0 | O196: 0 | P196: 0 | Q196: 0
A197: PS-INV181456 | B197: 11005 | C197: Dot Foods Inc. | D197: Item | E197: F530142 | F197: Cs. Knot Roll 8-12pk | G197: 46052 | I197: FG-DIST | J197: EBC | L197: 320 | M197: EA | N197: 33.42 | O197: 10694.4 | P197: 10694.4 | Q197: 0
A198: PS-INV181457 | B198: 10511 | C198: Sysco Nashville, LLC | D198: Item | E198: F53072 | F198: Cs. 5" Challah Bun 8-8pk | G198: 46050 | I198: FG-DIST | J198: EBC | L198: 16 | M198: EA | N198: 37.05 | O198: 592.8 | P198: 592.8 | Q198: 0
A199: PS-INV181457 | B199: 10511 | C199: Sysco Nashville, LLC | D199: Item | E199: F51200 | F199: Cs. Jalapeno Corn Hearth 5/8" 8lvs | G199: 46050 | I199: FG-DIST | J199: EBC | L199: 16 | M199: EA | N199: 60.07 | O199: 961.12 | P199: 961.12 | Q199: 0
A200: PS-INV181457 | B200: 10511 | C200: Sysco Nashville, LLC | D200: Item | E200: F53001 | F200: Cs. 4" Brioche Bun 8-12pk | G200: 46050 | I200: FG-DIST | J200: EBC | L200: 252 | M200: EA | N200: 46.1 | O200: 11617.2 | P200: 11617.2 | Q200: 0
A201: PS-INV181457 | B201: 10511 | C201: Sysco Nashville, LLC | D201: Item | E201: F53116 | F201: Cs. 7" French Hinged 12 | G201: 46050 | I201: FG-DIST | J201: EBC | L201: 48 | M201: EA | N201: 38 | O201: 1824 | P201: 1824 | Q201: 0
A202: PS-INV181457 | B202: 10511 | C202: Sysco Nashville, LLC | D202: Item | E202: F53128 | F202: Cs. 8" Philly Unsliced 10-6pk | G202: 46050 | I202: FG-DIST | J202: EBC | L202: 112 | M202: EA | N202: 45 | O202: 5040 | P202: 5040 | Q202: 0
A203: PS-INV181756 | B203: Z10700 | C203: Sysco-Charlotte | D203: Item | E203: F52564 | F203: Cs. Rye Batard 5/8" 8lvs | G203: 46035 | I203: FG-DIST | J203: EBC | L203: 32 | M203: EA | N203: 46.38 | O203: 1484.16 | P203: 1484.16 | Q203: 0
A204: PS-INV181880 | B204: 10155-45 | C204: Hammer and Spoon MTWTHF | D204: Item | E204: F56251 | F204: Cs. Challah Sliders Sliced 18-12pks | G204: 46035 | H204: DOMESTIC | I204: FG-DIST | J204: EBC | L204: 0 | M204: EA | N204: 0 | O204: 0 | P204: 0 | Q204: 0
A205: PS-INV181880 | B205: 10155-45 | C205: Hammer and Spoon MTWTHF | D205: Item | E205: F56560 | F205: Gluten Free 3.5" Hamburger 36ct | G205: 46035 | H205: DOMESTIC | I205: FG-DIST | J205: EBC | L205: 0 | M205: EA | N205: 0 | O205: 0 | P205: 0 | Q205: 0
A206: PS-INV181880 | B206: 10155-45 | C206: Hammer and Spoon MTWTHF | D206: Item | E206: F56255 | F206: Cs. English Muffin 30-6pk | G206: 46035 | H206: DOMESTIC | I206: FG-DIST | J206: EBC | L206: 0 | M206: EA | N206: 0 | O206: 0 | P206: 0 | Q206: 0
A207: PS-INV181948 | B207: 20334 | C207: Sysco Atlanta | D207: Item | E207: F53106 | F207: Cs. Large Hot Dog 12-6pk | G207: 46052 | I207: FG-DIST | J207: EBC | L207: 16 | M207: EA | N207: 36.5 | O207: 584 | P207: 584 | Q207: 0
A208: PS-INV181948 | B208: 20334 | C208: Sysco Atlanta | D208: Item | E208: F53116 | F208: Cs. 7" French Hinged 12 | G208: 46052 | I208: FG-DIST | J208: EBC | L208: 56 | M208: EA | N208: 31.42 | O208: 1759.52 | P208: 1759.52 | Q208: 0
A209: PS-INV181948 | B209: 20334 | C209: Sysco Atlanta | D209: Item | E209: F53087 | F209: Cs. 3.5" Challah Bun 8-12 pk | G209: 46052 | I209: FG-DIST | J209: EBC | L209: 84 | M209: EA | N209: 34 | O209: 2856 | P209: 2856 | Q209: 0
A210: PS-INV181948 | B210: 20334 | C210: Sysco Atlanta | D210: Item | E210: F51024 | F210: Cs. Marble Rye 5/8" 8lvs | G210: 46052 | I210: FG-DIST | J210: EBC | L210: 12 | M210: EA | N210: 43.26 | O210: 519.12 | P210: 519.12 | Q210: 0
A211: PS-INV181948 | B211: 20334 | C211: Sysco Atlanta | D211: Item | E211: F51127 | F211: Cs. Challah 3-Braid 8 | G211: 46052 | I211: FG-DIST | J211: EBC | L211: 20 | M211: EA | N211: 43.26 | O211: 865.2 | P211: 865.2 | Q211: 0
A212: PS-INV181948 | B212: 20334 | C212: Sysco Atlanta | D212: Item | E212: F53001 | F212: Cs. 4" Brioche Bun 8-12pk | G212: 46052 | I212: FG-DIST | J212: EBC | L212: 84 | M212: EA | N212: 43.36 | O212: 3642.24 | P212: 3642.24 | Q212: 0
A213: PS-INV181948 | B213: 20334 | C213: Sysco Atlanta | D213: Item | E213: F51034 | F213: Cs. Sour Dough Hearth 5/8" 8lvs | G213: 46052 | I213: FG-DIST | J213: EBC | L213: 20 | M213: EA | N213: 41.2 | O213: 824 | P213: 824 | Q213: 0
A214: PS-INV181948 | B214: 20334 | C214: Sysco Atlanta | D214: Item | E214: F51157 | F214: Cs. Challah Hearth 7/8" 8lvs | G214: 46052 | I214: FG-DIST | J214: EBC | L214: 12 | M214: EA | N214: 42.02 | O214: 504.24 | P214: 504.24 | Q214: 0
A215: PS-INV181948 | B215: 20334 | C215: Sysco Atlanta | D215: Item | E215: F53140 | F215: Cs. Knuckies 8" White 12-6pk | G215: 46052 | I215: FG-DIST | J215: EBC | L215: 20 | M215: EA | N215: 41 | O215: 820 | P215: 820 | Q215: 0
A216: PS-INV181986 | B216: 10700 | C216: Gordon Food Service - Douglas | D216: Item | E216: F53002 | F216: Cs. Sesame Bun 8-12pk | G216: 46050 | I216: FG-DIST | J216: EBC | L216: 36 | M216: EA | N216: 41.7 | O216: 1501.2 | P216: 1501.2 | Q216: 0
A217: PS-INV181986 | B217: 10700 | C217: Gordon Food Service - Douglas | D217: Item | E217: F51361 | F217: Cs. Honey Wheat Pullman 7/8" 10lvs | G217: 46050 | I217: FG-DIST | J217: EBC | L217: 36 | M217: EA | N217: 41.49 | O217: 1493.64 | P217: 1493.64 | Q217: 0
A218: PS-INV181986 | B218: 10700 | C218: Gordon Food Service - Douglas | D218: Item | E218: F51384 | F218: Cs. Challah Pullman 7/8" | G218: 46050 | I218: FG-DIST | J218: EBC | L218: 156 | M218: EA | N218: 48.49 | O218: 7564.44 | P218: 7564.44 | Q218: 0
... A228: PS-INV182105 | B228: 10719-9 | C228: US Foods -Carolinas/Ft.Mill | D228: Item | E228: F53003 | F228: Cs. 4" Unseeded Challah Bun 8-12pk | G228: 46055 | I228: FG-DIST | J228: EBC | L228: 144 | M228: EA | N228: 39 | O228: 5616 | P228: 5616 | Q228: 0
A229: PS-INV182288 | B229: 10155-45 | C229: Hammer and Spoon MTWTHF | D229: Item | E229: F56251 | F229: Cs. Challah Sliders Sliced 18-12pks | G229: 46036 | H229: DOMESTIC | I229: FG-DIST | J229: EBC | L229: 0 | M229: EA | N229: 0 | O229: 0 | P229: 0 | Q229: 0
A230: PS-INV182288 | B230: 10155-45 | C230: Hammer and Spoon MTWTHF | D230: Item | E230: F56560 | F230: Gluten Free 3.5" Hamburger 36ct | G230: 46036 | H230: DOMESTIC | I230: FG-DIST | J230: EBC | L230: 0 | M230: EA | N230: 0 | O230: 0 | P230: 0 | Q230: 0
A231: PS-INV182288 | B231: 10155-45 | C231: Hammer and Spoon MTWTHF | D231: Item | E231: F56255 | F231: Cs. English Muffin 30-6pk | G231: 46036 | H231: DOMESTIC | I231: FG-DIST | J231: EBC | L231: 0 | M231: EA | N231: 0 | O231: 0 | P231: 0 | Q231: 0
A232: PS-INV182442 | B232: 11394 | C232: La Cosecha Food Service | D232: Item | E232: F53127 | F232: Cs. 8" Philly 10-6pks | G232: 46043 | I232: FG-DIST | J232: EBC | L232: 12 | M232: EA | N232: 53.2 | O232: 638.4 | P232: 638.4 | Q232: 0
A233: PS-INV182442 | B233: 11394 | C233: La Cosecha Food Service | D233: Item | E233: F530401 | F233: Cs. 4.5" Sesame 6-12pk | G233: 46043 | I233: FG-DIST | J233: EBC | L233: 0 | M233: EA | N233: 34.18 | O233: 0 | P233: 0 | Q233: 0
A234: PS-INV182446 | B234: 10549 | C234: PFG Nashville TN | D234: Item | E234: F53002 | F234: Cs. Sesame Bun 8-12pk | G234: 46056 | I234: FG-DIST | J234: EBC | L234: 40 | M234: EA | N234: 37.5 | O234: 1500 | P234: 1500 | Q234: 0
A235: PS-INV182446 | B235: 10549 | C235: PFG Nashville TN | D235: Item | E235: F53003 | F235: Cs. 4" Unseeded Challah Bun 8-12pk | G235: 46056 | I235: FG-DIST | J235: EBC | L235: 56 | M235: EA | N235: 34.5 | O235: 1932 | P235: 1932 | Q235: 0
A236: PS-INV182446 | B236: 10549 | C236: PFG Nashville TN | D236: Item | E236: F53070 | F236: Cs. 5" Challah Sesame Buns | G236: 46056 | I236: FG-DIST | J236: EBC | L236: 32 | M236: EA | N236: 34.5 | O236: 1104 | P236: 1104 | Q236: 0
A237: PS-INV182718 | B237: 10719-3 | C237: US Foods - Raleigh/Zebulon | D237: Item | E237: F53002 | F237: Cs. Sesame Bun 8-12pk | G237: 46058 | I237: FG-DIST | J237: EBC | L237: 60 | M237: EA | N237: 41.66 | O237: 2499.6 | P237: 2499.6 | Q237: 0
A238: PS-INV182718 | B238: 10719-3 | C238: US Foods - Raleigh/Zebulon | D238: Item | E238: F52902 | F238: Cs. 22" Rye Baguette 10-2pk | G238: 46058 | I238: FG-DIST | J238: EBC | L238: 16 | M238: EA | N238: 42.53 | O238: 680.48 | P238: 680.48 | Q238: 0
A239: PS-INV182718 | B239: 10719-3 | C239: US Foods - Raleigh/Zebulon | D239: Item | E239: F52007 | F239: Cs. 22" 17oz French 10 | G239: 46058 | I239: FG-DIST | J239: EBC | L239: 32 | M239: EA | N239: 39.96 | O239: 1278.72 | P239: 1278.72 | Q239: 0
A240: PS-INV182718 | B240: 10719-3 | C240: US Foods - Raleigh/Zebulon | D240: Item | E240: F51026 | F240: Cs. Marble Rye 3/4" 8lvs | G240: 46058 | I240: FG-DIST | J240: EBC | L240: 24 | M240: EA | N240: 52 | O240: 1248 | P240: 1248 | Q240: 0
A241: PS-INV182727 | B241: 10138-5 | C241: Costco PriceSmart Export | D241: Item | E241: F53106 | F241: Cs. Large Hot Dog 12-6pk | G241: 46062 | I241: FG-DIST | J241: EBC | L241: 942 | M241: EA | N241: 26.25 | O241: 24727.5 | P241: 24727.5 | Q241: 0
A242: PS-INV182730 | B242: 20334 | C242: Sysco Atlanta | D242: Item | E242: F53116 | F242: Cs. 7" French Hinged 12 | G242: 46051 | I242: FG-DIST | J242: EBC | L242: 28 | M242: EA | N242: 31.42 | O242: 879.76 | P242: 879.76 | Q242: 0
A243: PS-INV182730 | B243: 20334 | C243: Sysco Atlanta | D243: Item | E243: F53087 | F243: Cs. 3.5" Challah Bun 8-12 pk | G243: 46051 | I243: FG-DIST | J243: EBC | L243: 140 | M243: EA | N243: 34 | O243: 4760 | P243: 4760 | Q243: 0
... A249: PS-INV182730 | B249: 20334 | C249: Sysco Atlanta | D249: Item | E249: F53140 | F249: Cs. Knuckies 8" White 12-6pk | G249: 46051 | I249: FG-DIST | J249: EBC | L249: 40 | M249: EA | N249: 41 | O249: 1640 | P249: 1640 | Q249: 0
A250: PS-INV182739 | B250: 13128 | C250: Gordon Food Service - Shepherdsville | D250: Item | E250: F51084 | F250: Cs. Wheatberry Hearth | G250: 46052 | H250: DOMESTIC | I250: FG-DIST | J250: EBC | L250: 80 | M250: EA | N250: 33.3 | O250: 2664 | P250: 2664 | Q250: 0
A251: PS-INV182739 | B251: 13128 | C251: Gordon Food Service - Shepherdsville | D251: Item | E251: F53001 | F251: Cs. 4" Brioche Bun 8-12pk | G251: 46052 | H251: DOMESTIC | I251: FG-DIST | J251: EBC | L251: 256 | M251: EA | N251: 36.82 | O251: 9425.92 | P251: 9425.92 | Q251: 0
A252: PS-INV182739 | B252: 13128 | C252: Gordon Food Service - Shepherdsville | D252: Item | E252: F51114 | F252: Cs. Old Fashioned Hearth 5/8" 8lvs | G252: 46052 | H252: DOMESTIC | I252: FG-DIST | J252: EBC | L252: 176 | M252: EA | N252: 39.7 | O252: 6987.2 | P252: 6987.2 | Q252: 0
A253: PS-INV182739 | B253: 13128 | C253: Gordon Food Service - Shepherdsville | D253: Item | E253: F56251 | F253: Cs. Challah Sliders Sliced 18-12pks | G253: 46052 | H253: DOMESTIC | I253: FG-DIST | J253: EBC | L253: 320 | M253: EA | N253: 39.7 | O253: 12704 | P253: 12704 | Q253: 0
...

Sheet Combined Invoices & Lines
A1: Document No. | B1: Sell-to Customer No. | C1: Sell-to Customer Name | D1: No. | E1: Description | F1: Posting Date | G1: Quantity | H1: Unit Price Excl. Tax | I1: Amount
A2: ='Posted Sales Invoice Lines'!A2 -> PS-INV173271 | B2: ='Posted Sales Invoice Lines'!B2 -> 10719-6 | C2: ='Posted Sales Invoice Lines'!C2 -> US Foods - Alcoa TN. | D2: ='Posted Sales Invoice Lines'!E2 -> F53094 | E2: ='Posted Sales Invoice Lines'!F2 -> Cs. 6" Italian 12-6pks | F2: ='Posted Sales Invoice Lines'!G2 -> 46027 | G2: ='Posted Sales Invoice Lines'!L2 -> 28 | H2: ='Posted Sales Invoice Lines'!N2 -> 35 | I2: ='Posted Sales Invoice Lines'!O2 -> 980
A3: ='Posted Sales Invoice Lines'!A3 -> PS-INV173271 | B3: ='Posted Sales Invoice Lines'!B3 -> 10719-6 | C3: ='Posted Sales Invoice Lines'!C3 -> US Foods - Alcoa TN. | D3: ='Posted Sales Invoice Lines'!E3 -> F51136 | E3: ='Posted Sales Invoice Lines'!F3 -> Cs. Texas Toast 1" 12lvs | F3: ='Posted Sales Invoice Lines'!G3 -> 46027 | G3: ='Posted Sales Invoice Lines'!L3 -> 84 | H3: ='Posted Sales Invoice Lines'!N3 -> 40.12 | I3: ='Posted Sales Invoice Lines'!O3 -> 3370.08
A4: ='Posted Sales Invoice Lines'!A4 -> PS-INV173271 | B4: ='Posted Sales Invoice Lines'!B4 -> 10719-6 | C4: ='Posted Sales Invoice Lines'!C4 -> US Foods - Alcoa TN. | D4: ='Posted Sales Invoice Lines'!E4 -> F51004 | E4: ='Posted Sales Invoice Lines'!F4 -> Cs. Rye 5/8" 8lvs | F4: ='Posted Sales Invoice Lines'!G4 -> 46027 | G4: ='Posted Sales Invoice Lines'!L4 -> 8 | H4: ='Posted Sales Invoice Lines'!N4 -> 42.03 | I4: ='Posted Sales Invoice Lines'!O4 -> 336.24
A5: ='Posted Sales Invoice Lines'!A5 -> PS-INV173271 | B5: ='Posted Sales Invoice Lines'!B5 -> 10719-6 | C5: ='Posted Sales Invoice Lines'!C5 -> US Foods - Alcoa TN. | D5: ='Posted Sales Invoice Lines'!E5 -> F53025 | E5: ='Posted Sales Invoice Lines'!F5 -> Cs. Sesame Challah Kaiser 8-12pk | F5: ='Posted Sales Invoice Lines'!G5 -> 46027 | G5: ='Posted Sales Invoice Lines'!L5 -> 308 | H5: ='Posted Sales Invoice Lines'!N5 -> 39 | I5: ='Posted Sales Invoice Lines'!O5 -> 12012
A6: ='Posted Sales Invoice Lines'!A6 -> PS-INV173271 | B6: ='Posted Sales Invoice Lines'!B6 -> 10719-6 | C6: ='Posted Sales Invoice Lines'!C6 -> US Foods - Alcoa TN. | D6: ='Posted Sales Invoice Lines'!E6 -> F53087 | E6: ='Posted Sales Invoice Lines'!F6 -> Cs. 3.5" Challah Bun 8-12 pk | F6: ='Posted Sales Invoice Lines'!G6 -> 46027 | G6: ='Posted Sales Invoice Lines'!L6 -> 28 | H6: ='Posted Sales Invoice Lines'!N6 -> 36.24 | I6: ='Posted Sales Invoice Lines'!O6 -> 1014.72
A7: ='Posted Sales Invoice Lines'!A7 -> PS-INV173271 | B7: ='Posted Sales Invoice Lines'!B7 -> 10719-6 | C7: ='Posted Sales Invoice Lines'!C7 -> US Foods - Alcoa TN. | D7: ='Posted Sales Invoice Lines'!E7 -> F51066 | E7: ='Posted Sales Invoice Lines'!F7 -> Cs. Honey Wheat 3/4" 8lvs | F7: ='Posted Sales Invoice Lines'!G7 -> 46027 | G7: ='Posted Sales Invoice Lines'!L7 -> 14 | H7: ='Posted Sales Invoice Lines'!N7 -> 35.21 | I7: ='Posted Sales Invoice Lines'!O7 -> 492.94
A8: ='Posted Sales Invoice Lines'!A8 -> PS-INV173271 | B8: ='Posted Sales Invoice Lines'!B8 -> 10719-6 | C8: ='Posted Sales Invoice Lines'!C8 -> US Foods - Alcoa TN. | D8: ='Posted Sales Invoice Lines'!E8 -> F53001 | E8: ='Posted Sales Invoice Lines'!F8 -> Cs. 4" Brioche Bun 8-12pk | F8: ='Posted Sales Invoice Lines'!G8 -> 46027 | G8: ='Posted Sales Invoice Lines'!L8 -> 140 | H8: ='Posted Sales Invoice Lines'!N8 -> 45.49 | I8: ='Posted Sales Invoice Lines'!O8 -> 6368.6
A9: ='Posted Sales Invoice Lines'!A9 -> PS-INV173271 | B9: ='Posted Sales Invoice Lines'!B9 -> 10719-6 | C9: ='Posted Sales Invoice Lines'!C9 -> US Foods - Alcoa TN. | D9: ='Posted Sales Invoice Lines'!E9 -> F530501 | E9: ='Posted Sales Invoice Lines'!F9 -> Cs. 4.5" Challah Kaiser 6-12pk | F9: ='Posted Sales Invoice Lines'!G9 -> 46027 | G9: ='Posted Sales Invoice Lines'!L9 -> 28 | H9: ='Posted Sales Invoice Lines'!N9 -> 37.02 | I9: ='Posted Sales Invoice Lines'!O9 -> 1036.56
A10: ='Posted Sales Invoice Lines'!A10 -> PS-INV173271 | B10: ='Posted Sales Invoice Lines'!B10 -> 10719-6 | C10: ='Posted Sales Invoice Lines'!C10 -> US Foods - Alcoa TN. | D10: ='Posted Sales Invoice Lines'!E10 -> F51084 | E10: ='Posted Sales Invoice Lines'!F10 -> Cs. Wheatberry Hearth | F10: ='Posted Sales Invoice Lines'!G10 -> 46027 | G10: ='Posted Sales Invoice Lines'!L10 -> 4 | H10: ='Posted Sales Invoice Lines'!N10 -> 52.47 | I10: ='Posted Sales Invoice Lines'!O10 -> 209.88
A11: ='Posted Sales Invoice Lines'!A11 -> PS-INV173271 | B11: ='Posted Sales Invoice Lines'!B11 -> 10719-6 | C11: ='Posted Sales Invoice Lines'!C11 -> US Foods - Alcoa TN. | D11: ='Posted Sales Invoice Lines'!E11 -> F51024 | E11: ='Posted Sales Invoice Lines'!F11 -> Cs. Marble Rye 5/8" 8lvs | F11: ='Posted Sales Invoice Lines'!G11 -> 46027 | G11: ='Posted Sales Invoice Lines'!L11 -> 4 | H11: ='Posted Sales Invoice Lines'!N11 -> 54 | I11: ='Posted Sales Invoice Lines'!O11 -> 216
A12: ='Posted Sales Invoice Lines'!A12 -> PS-INV173271 | B12: ='Posted Sales Invoice Lines'!B12 -> 10719-6 | C12: ='Posted Sales Invoice Lines'!C12 -> US Foods - Alcoa TN. | D12: ='Posted Sales Invoice Lines'!E12 -> F51034 | E12: ='Posted Sales Invoice Lines'!F12 -> Cs. Sour Dough Hearth 5/8" 8lvs | F12: ='Posted Sales Invoice Lines'!G12 -> 46027 | G12: ='Posted Sales Invoice Lines'!L12 -> 8 | H12: ='Posted Sales Invoice Lines'!N12 -> 43.2 | I12: ='Posted Sales Invoice Lines'!O12 -> 345.6
A13: ='Posted Sales Invoice Lines'!A13 -> PS-INV173271 | B13: ='Posted Sales Invoice Lines'!B13 -> 10719-6 | C13: ='Posted Sales Invoice Lines'!C13 -> US Foods - Alcoa TN. | D13: ='Posted Sales Invoice Lines'!E13 -> F51157 | E13: ='Posted Sales Invoice Lines'!F13 -> Cs. Challah Hearth 7/8" 8lvs | F13: ='Posted Sales Invoice Lines'!G13 -> 46027 | G13: ='Posted Sales Invoice Lines'!L13 -> 28 | H13: ='Posted Sales Invoice Lines'!N13 -> 44.15 | I13: ='Posted Sales Invoice Lines'!O13 -> 1236.2
... A1891: ='Posted Sales Invoice Lines'!A1891 -> PS-INV231387 | B1891: ='Posted Sales Invoice Lines'!B1891 -> 1-4 | C1891: ='Posted Sales Invoice Lines'!C1891 -> Heath West | D1891: ='Posted Sales Invoice Lines'!E1891 -> F56251 | E1891: ='Posted Sales Invoice Lines'!F1891 -> Cs. Challah Sliders Sliced 18-12pks | F1891: ='Posted Sales Invoice Lines'!G1891 -> 46196 | G1891: ='Posted Sales Invoice Lines'!L1891 -> 1 | H1891: ='Posted Sales Invoice Lines'!N1891 -> 0 | I1891: ='Posted Sales Invoice Lines'!O1891 -> 0
